Changelog
MANIFEST.in
README.md
README.rst
setup.py
doc/ichorORM.WhereClause.html
doc/ichorORM.connection.html
doc/ichorORM.constants.html
doc/ichorORM.html
doc/ichorORM.model.html
doc/ichorORM.objs.html
doc/ichorORM.query.html
doc/ichorORM.relations.html
doc/ichorORM.special.html
doc/ichorORM.utils.html
doc/index.html
ichorORM/WhereClause.py
ichorORM/__init__.py
ichorORM/connection.py
ichorORM/constants.py
ichorORM/model.py
ichorORM/objs.py
ichorORM/query.py
ichorORM/relations.py
ichorORM/special.py
ichorORM/utils.py
ichorORM.egg-info/PKG-INFO
ichorORM.egg-info/SOURCES.txt
ichorORM.egg-info/dependency_links.txt
ichorORM.egg-info/requires.txt
ichorORM.egg-info/top_level.txt
tests/runTests.py
tests/ichorORMTests/IchorTestInternal.py
tests/ichorORMTests/LocalConfig.py
tests/ichorORMTests/test_DatabaseConnection.py
tests/ichorORMTests/test_DatabaseModel.py
tests/ichorORMTests/test_DeleteQuery.py
tests/ichorORMTests/test_Dummy.py
tests/ichorORMTests/test_InsertQuery.py
tests/ichorORMTests/test_Relations.py
tests/ichorORMTests/test_SelectGenericJoinQuery.py
tests/ichorORMTests/test_SelectInnerJoinQuery.py
tests/ichorORMTests/test_SelectQuery.py
tests/ichorORMTests/test_UpdateQuery.py
tests/ichorORMTests/ichor_test_models/Meal.py
tests/ichorORMTests/ichor_test_models/Person.py
tests/ichorORMTests/ichor_test_models/__init__.py
tests/ichorORMTests/ichor_test_models/all.py